{"balance": 10115166.43373342, "krw_balance": 10115166.43373342, "pos_value": 0, "total_pnl": 115166.43373341963, "total_asset_pnl": 115166.43373341963, "total_trades": 587, "wins": 191, "losses": 200, "draws": 196, "win_rate": 32.5, "today_pnl": -25102.94982082781, "today_trades": 51, "today_wr": 29.4, "daily": [{"date": "2026-04-13", "pnl": 15738.622743407846, "trades": 19, "wins": 7, "losses": 7, "draws": 5, "win_rate": 36.8}, {"date": "2026-04-14", "pnl": -18604.5889293598, "trades": 74, "wins": 25, "losses": 29, "draws": 20, "win_rate": 33.8}, {"date": "2026-04-15", "pnl": 145220.00795033714, "trades": 145, "wins": 52, "losses": 54, "draws": 39, "win_rate": 35.9}, {"date": "2026-04-16", "pnl": 83886.88223717106, "trades": 159, "wins": 51, "losses": 47, "draws": 61, "win_rate": 32.1}, {"date": "2026-04-17", "pnl": -85971.5404473088, "trades": 139, "wins": 41, "losses": 49, "draws": 49, "win_rate": 29.5}, {"date": "2026-04-18", "pnl": -25102.94982082781, "trades": 51, "wins": 15, "losses": 14, "draws": 22, "win_rate": 29.4}], "batches": [{"batch": "batch_1", "total": 558, "win_rate": 32.437275985663085, "pnl": 133270.29040093953}, {"batch": "batch_2", "total": 1, "win_rate": 0.0, "pnl": 0}, {"batch": "surge_trade", "total": 28, "win_rate": 35.714285714285715, "pnl": -18103.856667519896}], "recent": [{"time": "04-18T09:12", "coin": "LSK", "profit": 0, "profit_rate": 0, "batch": "batch_1"}, {"time": "04-18T09:10", "coin": "AXL", "profit": -5464.0, "profit_rate": -0.546448087431694, "batch": "surge_trade"}, {"time": "04-18T09:00", "coin": "MLK", "profit": 952.3936708860565, "profit_rate": 0.12658227848101009, "batch": "batch_1"}, {"time": "04-18T08:55", "coin": "ZBT", "profit": -8501.593220338924, "profit_rate": -1.129943502824851, "batch": "batch_1"}, {"time": "04-18T08:44", "coin": "ETHFI", "profit": 992.6002638522768, "profit_rate": 0.1319261213720362, "batch": "batch_1"}, {"time": "04-18T08:44", "coin": "INJ", "profit": 303.4446460979525, "profit_rate": 0.04033071183705712, "batch": "batch_1"}, {"time": "04-18T08:40", "coin": "PENDLE", "profit": -12268.937040441204, "profit_rate": -3.2628676470588305, "batch": "batch_1"}, {"time": "04-18T08:39", "coin": "ARKM", "profit": 0, "profit_rate": 0, "batch": "batch_1"}, {"time": "04-18T08:13", "coin": "IOST", "profit": 0, "profit_rate": 0, "batch": "batch_1"}, {"time": "04-18T08:12", "coin": "XEC", "profit": -6778.297297297278, "profit_rate": -0.9009009009008985, "batch": "batch_1"}, {"time": "04-18T08:09", "coin": "SKY", "profit": 0, "profit_rate": 0, "batch": "batch_1"}, {"time": "04-18T08:05", "coin": "IMX", "profit": 0, "profit_rate": 0, "batch": "batch_1"}, {"time": "04-18T07:54", "coin": "ICP", "profit": -1351.1922484600218, "profit_rate": -0.1796714579055525, "batch": "batch_1"}, {"time": "04-18T07:48", "coin": "AERGO", "profit": -900.6407185627613, "profit_rate": -0.11976047904190117, "batch": "batch_1"}, {"time": "04-18T07:45", "coin": "AXS", "profit": 427.88781321188435, "profit_rate": 0.056947608200460804, "batch": "batch_1"}, {"time": "04-18T07:32", "coin": "QKC", "profit": 0, "profit_rate": 0, "batch": "batch_1"}, {"time": "04-18T07:28", "coin": "MEW", "profit": 799.3308510638308, "profit_rate": 0.10638297872340438, "batch": "batch_1"}, {"time": "04-18T07:25", "coin": "XTZ", "profit": 0, "profit_rate": 0, "batch": "batch_1"}, {"time": "04-18T07:22", "coin": "WLD", "profit": -5314.949999999953, "profit_rate": -0.714285714285708, "batch": "batch_1"}, {"time": "04-18T07:11", "coin": "LA", "profit": 2941.0790513833053, "profit_rate": 0.3952569169960348, "batch": "batch_1"}], "coins": [{"coin": "ZBT", "total": 7, "wins": 1, "losses": 2, "win_rate": 14.3, "pnl": -9256.709974106983}, {"coin": "TRUST", "total": 7, "wins": 2, "losses": 1, "win_rate": 28.6, "pnl": 18921.873990531894}, {"coin": "IOST", "total": 7, "wins": 0, "losses": 1, "win_rate": 0.0, "pnl": -3746.9822485207114}, {"coin": "SUN", "total": 6, "wins": 2, "losses": 0, "win_rate": 33.3, "pnl": 3595.9609462657245}, {"coin": "PENDLE", "total": 6, "wins": 3, "losses": 2, "win_rate": 50.0, "pnl": 13109.808437136817}, {"coin": "IN", "total": 6, "wins": 5, "losses": 1, "win_rate": 83.3, "pnl": 137261.1151648393}, {"coin": "ENSO", "total": 6, "wins": 5, "losses": 1, "win_rate": 83.3, "pnl": 4638.966215458931}, {"coin": "CVC", "total": 6, "wins": 3, "losses": 2, "win_rate": 50.0, "pnl": 2857.5308255301206}, {"coin": "XEC", "total": 5, "wins": 0, "losses": 1, "win_rate": 0.0, "pnl": -6778.297297297278}, {"coin": "VANA", "total": 5, "wins": 2, "losses": 3, "win_rate": 40.0, "pnl": -13620.078265248332}, {"coin": "SC", "total": 5, "wins": 1, "losses": 1, "win_rate": 20.0, "pnl": 773.7332332096994}, {"coin": "SAHARA", "total": 5, "wins": 1, "losses": 1, "win_rate": 20.0, "pnl": 2338.329381456715}, {"coin": "PLUME", "total": 5, "wins": 2, "losses": 2, "win_rate": 40.0, "pnl": 14707.2468468101}, {"coin": "ORDER", "total": 5, "wins": 3, "losses": 2, "win_rate": 60.0, "pnl": 17389.477878186444}, {"coin": "OP", "total": 5, "wins": 2, "losses": 1, "win_rate": 40.0, "pnl": 2751.8482630756916}, {"coin": "MOC", "total": 5, "wins": 2, "losses": 1, "win_rate": 40.0, "pnl": 1229.3232415559469}, {"coin": "LAYER", "total": 5, "wins": 1, "losses": 1, "win_rate": 20.0, "pnl": -16.68030303029809}, {"coin": "LA", "total": 5, "wins": 3, "losses": 1, "win_rate": 60.0, "pnl": 3912.2270243800012}, {"coin": "ERA", "total": 5, "wins": 2, "losses": 1, "win_rate": 40.0, "pnl": 3212.809436128009}, {"coin": "BREV", "total": 5, "wins": 1, "losses": 1, "win_rate": 20.0, "pnl": -2778.0286119941156}, {"coin": "AXL", "total": 5, "wins": 2, "losses": 3, "win_rate": 40.0, "pnl": -6544.40842795989}, {"coin": "ATH", "total": 5, "wins": 3, "losses": 2, "win_rate": 60.0, "pnl": 1633.947113833041}, {"coin": "ZORA", "total": 4, "wins": 0, "losses": 2, "win_rate": 0.0, "pnl": -5510.111042183591}, {"coin": "ZIL", "total": 4, "wins": 1, "losses": 1, "win_rate": 25.0, "pnl": -154.3020851382753}, {"coin": "ZETA", "total": 4, "wins": 2, "losses": 2, "win_rate": 50.0, "pnl": -5648.728052179911}, {"coin": "WAVES", "total": 4, "wins": 0, "losses": 1, "win_rate": 0.0, "pnl": -1418.4276422763942}, {"coin": "VTHO", "total": 4, "wins": 1, "losses": 1, "win_rate": 25.0, "pnl": -6.817104657180607}, {"coin": "T", "total": 4, "wins": 1, "losses": 0, "win_rate": 25.0, "pnl": 1.1641532182693481e-10}, {"coin": "SOMI", "total": 4, "wins": 2, "losses": 0, "win_rate": 50.0, "pnl": 5257.0507659313735}, {"coin": "RAY", "total": 4, "wins": 2, "losses": 1, "win_rate": 50.0, "pnl": -1179.193362566526}], "changelog": [{"time": "2026-04-15T17:26", "type": "cooldown_extend", "desc": "재진입 승률 25% (1/4건)"}, {"time": "2026-04-15T01:09", "type": "weight_adjust", "desc": "고모멘텀 수익 -0.82% < 저모멘텀 -0.05% → 거래량/RSI↑ 패턴/뉴스↓"}, {"time": "2026-04-14T21:41", "type": "momentum_boost", "desc": "4시 승률 14% (1/7건)"}, {"time": "2026-04-14T14:42", "type": "trailing_adjust", "desc": "고점 놓침 17/36건 (47%)"}, {"time": "2026-04-13T20:41", "type": "stoploss_adjust", "desc": "평균 손실 -23.81% (너무 늦음)"}], "positions": [], "hourly": [{"hour": 0, "cnt": 9, "wins": 2, "wr": 22.2, "pnl": -19016}, {"hour": 1, "cnt": 5, "wins": 4, "wr": 80.0, "pnl": 17379}, {"hour": 2, "cnt": 4, "wins": 4, "wr": 100.0, "pnl": 7615}, {"hour": 3, "cnt": 8, "wins": 5, "wr": 62.5, "pnl": 1955}, {"hour": 4, "cnt": 10, "wins": 6, "wr": 60.0, "pnl": 4153}, {"hour": 5, "cnt": 11, "wins": 6, "wr": 54.5, "pnl": 10709}, {"hour": 6, "cnt": 20, "wins": 7, "wr": 35.0, "pnl": -6060}, {"hour": 7, "cnt": 35, "wins": 19, "wr": 54.3, "pnl": 41632}, {"hour": 8, "cnt": 15, "wins": 6, "wr": 40.0, "pnl": -52109}, {"hour": 9, "cnt": 15, "wins": 9, "wr": 60.0, "pnl": 41171}, {"hour": 10, "cnt": 11, "wins": 8, "wr": 72.7, "pnl": 25535}, {"hour": 11, "cnt": 17, "wins": 12, "wr": 70.6, "pnl": 96661}, {"hour": 12, "cnt": 14, "wins": 8, "wr": 57.1, "pnl": 17485}, {"hour": 13, "cnt": 17, "wins": 7, "wr": 41.2, "pnl": -29269}, {"hour": 14, "cnt": 23, "wins": 6, "wr": 26.1, "pnl": -41718}, {"hour": 15, "cnt": 21, "wins": 14, "wr": 66.7, "pnl": 159252}, {"hour": 16, "cnt": 20, "wins": 10, "wr": 50.0, "pnl": 4378}, {"hour": 17, "cnt": 34, "wins": 15, "wr": 44.1, "pnl": -27882}, {"hour": 18, "cnt": 25, "wins": 13, "wr": 52.0, "pnl": -29000}, {"hour": 19, "cnt": 20, "wins": 7, "wr": 35.0, "pnl": -36772}, {"hour": 20, "cnt": 24, "wins": 8, "wr": 33.3, "pnl": -58460}, {"hour": 21, "cnt": 12, "wins": 4, "wr": 33.3, "pnl": -16795}, {"hour": 22, "cnt": 14, "wins": 7, "wr": 50.0, "pnl": 9087}, {"hour": 23, "cnt": 7, "wins": 4, "wr": 57.1, "pnl": -4762}], "surge_watchlist": 0, "bot_running": true, "bot_mode": "demo", "momentum": {"top10": [{"coin": "NXPC", "score": 27.7}, {"coin": "APT", "score": 26.1}, {"coin": "TRUMP", "score": 23.3}, {"coin": "HOLO", "score": 21.6}, {"coin": "COW", "score": 19.4}, {"coin": "MMT", "score": 18.5}, {"coin": "ETH", "score": 16.5}, {"coin": "ESP", "score": 14.9}, {"coin": "CARV", "score": 13.8}], "threshold": 15.0, "market_pct": {"p10": 6.9, "p20": 3.9, "median": 0.4}}, "market": {"grade": "보통", "color": "#f0c040", "btc_chg": 0.0, "alt_chg": -0.12, "detail": "횡보 구간"}, "ai_stats": {"total_lessons": 270, "mistakes": [{"type": "overchase", "count": 118}, {"type": "early_exit", "count": 81}, {"type": "timing", "count": 42}, {"type": "ignore_trend", "count": 12}, {"type": "overchase + early_exit", "count": 1}, {"type": "mixed", "count": 1}, {"type": "early_exit|overchase", "count": 1}, {"type": "early_exit | overchase (약한 신호 충동진입)", "count": 1}], "avg_severity": 2.3}, "rr_stats": {"avg_win": 4839, "avg_loss": -4045, "rr_ratio": 1.2, "biggest_win": 138478, "biggest_loss": -25375}, "equity_curve": [{"date": "2026-04-13", "equity": 15739}, {"date": "2026-04-14", "equity": -2866}, {"date": "2026-04-15", "equity": 142354}, {"date": "2026-04-16", "equity": 226241}, {"date": "2026-04-17", "equity": 140269}, {"date": "2026-04-18", "equity": 115166}], "ai_decisions": [], "version": "1.2.1", "updated": "04/18 09:48:49"}